verilog/cla.v
module CLA_Adder(cin,a1,a2,a3,a4,b1,b2,b3,b4,s1,s2,s3,s4,cout);
input cin,a1,a2,a3,a4,b1,b2,b3,b4;
output s1,s2,s3,s4,cout;
wire p1,p2,p3,p4,g1,g2,g3,g4,t1,t2,t3,t4,t5,t6;

// propagate and generate
xor #1 (p1,a1,b1);
xor #2 (p2,a2,b2);
xor #3 (p3,a3,b3);
xor #4 (p4,a4,b4);

and #1 (g1,a1,b1);
and #2 (g2,a2,b2);
and #3 (g3,a3,b3);
and #4 (g4,a4,b4);

// carry 
// C1
and #5 (t1, p1, cin);
or #1 (c1, g1, t1);

// C2
and #6 (t2, p1, p2, cin);
and #7 (t3, g1, p2);
or #2 (c2, t2, t3, g1);

// C3
and #8 (t4, p1, p2, p3, cin);
and #9 (t5, g1, p2, p3);
and #10 (t6, g2, p3);
or #3 (c3, g2, t6, t5, t4);

// C4
and #11 (t7, p1, p2, p3, p4, cin);
and #12 (t8, g1, p2, p3, p4);
and #13(t9, g2, p3, p4);
and #14(t10, g3, p4);
or #4 (c4, g3, t10, t9, t8, t7);

// sum
xor #5 (s1,p1,c1);
xor #6 (s2,p2,c2);
xor #7 (s3,p3,c3);
xor #8 (s4,p4,c4);

endmodule

verilog/clatest.v
module testbench;
reg cin,a1,a2,a3,a4,b1,b2,b3,b4; 
wire s1,s2,s3,s4,c5;
CLA_Adder DUT(cin,a1,a2,a3,a4,b1,b2,b3,b4,s1,s2,s3,s4,cout);

initial begin
$dumpfile("cla.vcd");
$dumpvars(0,testbench);
//print statement
$monitor($time," A=%b%b%b%b B=%b%b%b%b Cout=%b S=%b%b%b%b",a4,a3,a2,a1,b4,b3,b2,b1,cout,s4,s3,s2,s1);
    cin = 1'b1;
    a1 = 1'b1;
    b1 = 1'b1;
    a2 = 1'b1;
    b2 = 1'b1;
    a3 = 1'b1;
    b3 = 1'b1;
    a4 = 1'b1;
    b4 = 1'b1;

    #2560 $finish;
end
always #5 a1 = ~a1; 
// always b1 = ~b1;
// always a2 = ~a2;
// always b2 = ~b2;
// always a3 = ~a3;
// always b3 = ~b3;
// always a4 = ~a4;
// always b4 = ~b4;
// always #1280 cin = ~cin;
endmodule

verilog/cla.vcd
$date
	Thu Dec  9 12:36:31 2021
$end
$version
	Icarus Verilog
$end
$timescale
	1s
$end
$scope module testbench $end
$var wire 1 ! cout $end
$var wire 1 " s4 $end
$var wire 1 # s3 $end
$var wire 1 $ s2 $end
$var wire 1 % s1 $end
$var reg 1 & a1 $end
$var reg 1 ' a2 $end
$var reg 1 ( a3 $end
$var reg 1 ) a4 $end
$var reg 1 * b1 $end
$var reg 1 + b2 $end
$var reg 1 , b3 $end
$var reg 1 - b4 $end
$var reg 1 . cin $end
$scope module DUT $end
$var wire 1 & a1 $end
$var wire 1 ' a2 $end
$var wire 1 ( a3 $end
$var wire 1 ) a4 $end
$var wire 1 * b1 $end
$var wire 1 + b2 $end
$var wire 1 , b3 $end
$var wire 1 - b4 $end
$var wire 1 / c1 $end
$var wire 1 0 c2 $end
$var wire 1 1 c3 $end
$var wire 1 2 c4 $end
$var wire 1 . cin $end
$var wire 1 ! cout $end
$var wire 1 3 g1 $end
$var wire 1 4 g2 $end
$var wire 1 5 g3 $end
$var wire 1 6 g4 $end
$var wire 1 7 p1 $end
$var wire 1 8 p2 $end
$var wire 1 9 p3 $end
$var wire 1 : p4 $end
$var wire 1 % s1 $end
$var wire 1 $ s2 $end
$var wire 1 # s3 $end
$var wire 1 " s4 $end
$var wire 1 ; t1 $end
$var wire 1 < t10 $end
$var wire 1 = t2 $end
$var wire 1 > t3 $end
$var wire 1 ? t4 $end
$var wire 1 @ t5 $end
$var wire 1 A t6 $end
$var wire 1 B t7 $end
$var wire 1 C t8 $end
$var wire 1 D t9 $end
$upscope $end
$upscope $end
$enddefinitions $end
#0
$dumpvars
xD
xC
xB
xA
x@
x?
x>
x=
x<
x;
x:
x9
x8
x7
x6
x5
x4
x3
x2
x1
x0
x/
1.
1-
1,
1+
1*
1)
1(
1'
1&
x%
x$
x#
x"
z!
$end
#1
13
07
#2
1/
14
08
#3
10
15
09
#4
16
0:
#5
11
0&
#6
17
03
0;
#7
0/
12
0=
#8
x0
#9
0>
0?
#10
1&
#11
07
13
00
1;
0@
#12
1/
1#
0B
#13
10
0A
#14
0C
#15
0&
1"
#16
17
03
0;
0D
#17
0/
#18
00
0<
#20
1&
#21
07
13
1;
#22
1/
#23
10
#25
0&
#26
17
03
0;
#27
0/
#28
00
#30
1&
#31
07
13
1;
#32
1/
#33
10
#35
0&
#36
17
03
0;
#37
0/
#38
00
#40
1&
#41
07
13
1;
#42
1/
#43
10
#45
0&
#46
17
03
0;
#47
0/
#48
00
#50
1&
#51
07
13
1;
#52
1/
#53
10
#55
0&
#56
17
03
0;
#57
0/
#58
00
#60
1&
#61
07
13
1;
#62
1/
#63
10
#65
0&
#66
17
03
0;
#67
0/
#68
00
#70
1&
#71
07
13
1;
#72
1/
#73
10
#75
0&
#76
17
03
0;
#77
0/
#78
00
#80
1&
#81
07
13
1;
#82
1/
#83
10
#85
0&
#86
17
03
0;
#87
0/
#88
00
#90
1&
#91
07
13
1;
#92
1/
#93
10
#95
0&
#96
17
03
0;
#97
0/
#98
00
#100
1&
#101
07
13
1;
#102
1/
#103
10
#105
0&
#106
17
03
0;
#107
0/
#108
00
#110
1&
#111
07
13
1;
#112
1/
#113
10
#115
0&
#116
17
03
0;
#117
0/
#118
00
#120
1&
#121
07
13
1;
#122
1/
#123
10
#125
0&
#126
17
03
0;
#127
0/
#128
00
#130
1&
#131
07
13
1;
#132
1/
#133
10
#135
0&
#136
17
03
0;
#137
0/
#138
00
#140
1&
#141
07
13
1;
#142
1/
#143
10
#145
0&
#146
17
03
0;
#147
0/
#148
00
#150
1&
#151
07
13
1;
#152
1/
#153
10
#155
0&
#156
17
03
0;
#157
0/
#158
00
#160
1&
#161
07
13
1;
#162
1/
#163
10
#165
0&
#166
17
03
0;
#167
0/
#168
00
#170
1&
#171
07
13
1;
#172
1/
#173
10
#175
0&
#176
17
03
0;
#177
0/
#178
00
#180
1&
#181
07
13
1;
#182
1/
#183
10
#185
0&
#186
17
03
0;
#187
0/
#188
00
#190
1&
#191
07
13
1;
#192
1/
#193
10
#195
0&
#196
17
03
0;
#197
0/
#198
00
#200
1&
#201
07
13
1;
#202
1/
#203
10
#205
0&
#206
17
03
0;
#207
0/
#208
00
#210
1&
#211
07
13
1;
#212
1/
#213
10
#215
0&
#216
17
03
0;
#217
0/
#218
00
#220
1&
#221
07
13
1;
#222
1/
#223
10
#225
0&
#226
17
03
0;
#227
0/
#228
00
#230
1&
#231
07
13
1;
#232
1/
#233
10
#235
0&
#236
17
03
0;
#237
0/
#238
00
#240
1&
#241
07
13
1;
#242
1/
#243
10
#245
0&
#246
17
03
0;
#247
0/
#248
00
#250
1&
#251
07
13
1;
#252
1/
#253
10
#255
0&
#256
17
03
0;
#257
0/
#258
00
#260
1&
#261
07
13
1;
#262
1/
#263
10
#265
0&
#266
17
03
0;
#267
0/
#268
00
#270
1&
#271
07
13
1;
#272
1/
#273
10
#275
0&
#276
17
03
0;
#277
0/
#278
00
#280
1&
#281
07
13
1;
#282
1/
#283
10
#285
0&
#286
17
03
0;
#287
0/
#288
00
#290
1&
#291
07
13
1;
#292
1/
#293
10
#295
0&
#296
17
03
0;
#297
0/
#298
00
#300
1&
#301
07
13
1;
#302
1/
#303
10
#305
0&
#306
17
03
0;
#307
0/
#308
00
#310
1&
#311
07
13
1;
#312
1/
#313
10
#315
0&
#316
17
03
0;
#317
0/
#318
00
#320
1&
#321
07
13
1;
#322
1/
#323
10
#325
0&
#326
17
03
0;
#327
0/
#328
00
#330
1&
#331
07
13
1;
#332
1/
#333
10
#335
0&
#336
17
03
0;
#337
0/
#338
00
#340
1&
#341
07
13
1;
#342
1/
#343
10
#345
0&
#346
17
03
0;
#347
0/
#348
00
#350
1&
#351
07
13
1;
#352
1/
#353
10
#355
0&
#356
17
03
0;
#357
0/
#358
00
#360
1&
#361
07
13
1;
#362
1/
#363
10
#365
0&
#366
17
03
0;
#367
0/
#368
00
#370
1&
#371
07
13
1;
#372
1/
#373
10
#375
0&
#376
17
03
0;
#377
0/
#378
00
#380
1&
#381
07
13
1;
#382
1/
#383
10
#385
0&
#386
17
03
0;
#387
0/
#388
00
#390
1&
#391
07
13
1;
#392
1/
#393
10
#395
0&
#396
17
03
0;
#397
0/
#398
00
#400
1&
#401
07
13
1;
#402
1/
#403
10
#405
0&
#406
17
03
0;
#407
0/
#408
00
#410
1&
#411
07
13
1;
#412
1/
#413
10
#415
0&
#416
17
03
0;
#417
0/
#418
00
#420
1&
#421
07
13
1;
#422
1/
#423
10
#425
0&
#426
17
03
0;
#427
0/
#428
00
#430
1&
#431
07
13
1;
#432
1/
#433
10
#435
0&
#436
17
03
0;
#437
0/
#438
00
#440
1&
#441
07
13
1;
#442
1/
#443
10
#445
0&
#446
17
03
0;
#447
0/
#448
00
#450
1&
#451
07
13
1;
#452
1/
#453
10
#455
0&
#456
17
03
0;
#457
0/
#458
00
#460
1&
#461
07
13
1;
#462
1/
#463
10
#465
0&
#466
17
03
0;
#467
0/
#468
00
#470
1&
#471
07
13
1;
#472
1/
#473
10
#475
0&
#476
17
03
0;
#477
0/
#478
00
#480
1&
#481
07
13
1;
#482
1/
#483
10
#485
0&
#486
17
03
0;
#487
0/
#488
00
#490
1&
#491
07
13
1;
#492
1/
#493
10
#495
0&
#496
17
03
0;
#497
0/
#498
00
#500
1&
#501
07
13
1;
#502
1/
#503
10
#505
0&
#506
17
03
0;
#507
0/
#508
00
#510
1&
#511
07
13
1;
#512
1/
#513
10
#515
0&
#516
17
03
0;
#517
0/
#518
00
#520
1&
#521
07
13
1;
#522
1/
#523
10
#525
0&
#526
17
03
0;
#527
0/
#528
00
#530
1&
#531
07
13
1;
#532
1/
#533
10
#535
0&
#536
17
03
0;
#537
0/
#538
00
#540
1&
#541
07
13
1;
#542
1/
#543
10
#545
0&
#546
17
03
0;
#547
0/
#548
00
#550
1&
#551
07
13
1;
#552
1/
#553
10
#555
0&
#556
17
03
0;
#557
0/
#558
00
#560
1&
#561
07
13
1;
#562
1/
#563
10
#565
0&
#566
17
03
0;
#567
0/
#568
00
#570
1&
#571
07
13
1;
#572
1/
#573
10
#575
0&
#576
17
03
0;
#577
0/
#578
00
#580
1&
#581
07
13
1;
#582
1/
#583
10
#585
0&
#586
17
03
0;
#587
0/
#588
00
#590
1&
#591
07
13
1;
#592
1/
#593
10
#595
0&
#596
17
03
0;
#597
0/
#598
00
#600
1&
#601
07
13
1;
#602
1/
#603
10
#605
0&
#606
17
03
0;
#607
0/
#608
00
#610
1&
#611
07
13
1;
#612
1/
#613
10
#615
0&
#616
17
03
0;
#617
0/
#618
00
#620
1&
#621
07
13
1;
#622
1/
#623
10
#625
0&
#626
17
03
0;
#627
0/
#628
00
#630
1&
#631
07
13
1;
#632
1/
#633
10
#635
0&
#636
17
03
0;
#637
0/
#638
00
#640
1&
#641
07
13
1;
#642
1/
#643
10
#645
0&
#646
17
03
0;
#647
0/
#648
00
#650
1&
#651
07
13
1;
#652
1/
#653
10
#655
0&
#656
17
03
0;
#657
0/
#658
00
#660
1&
#661
07
13
1;
#662
1/
#663
10
#665
0&
#666
17
03
0;
#667
0/
#668
00
#670
1&
#671
07
13
1;
#672
1/
#673
10
#675
0&
#676
17
03
0;
#677
0/
#678
00
#680
1&
#681
07
13
1;
#682
1/
#683
10
#685
0&
#686
17
03
0;
#687
0/
#688
00
#690
1&
#691
07
13
1;
#692
1/
#693
10
#695
0&
#696
17
03
0;
#697
0/
#698
00
#700
1&
#701
07
13
1;
#702
1/
#703
10
#705
0&
#706
17
03
0;
#707
0/
#708
00
#710
1&
#711
07
13
1;
#712
1/
#713
10
#715
0&
#716
17
03
0;
#717
0/
#718
00
#720
1&
#721
07
13
1;
#722
1/
#723
10
#725
0&
#726
17
03
0;
#727
0/
#728
00
#730
1&
#731
07
13
1;
#732
1/
#733
10
#735
0&
#736
17
03
0;
#737
0/
#738
00
#740
1&
#741
07
13
1;
#742
1/
#743
10
#745
0&
#746
17
03
0;
#747
0/
#748
00
#750
1&
#751
07
13
1;
#752
1/
#753
10
#755
0&
#756
17
03
0;
#757
0/
#758
00
#760
1&
#761
07
13
1;
#762
1/
#763
10
#765
0&
#766
17
03
0;
#767
0/
#768
00
#770
1&
#771
07
13
1;
#772
1/
#773
10
#775
0&
#776
17
03
0;
#777
0/
#778
00
#780
1&
#781
07
13
1;
#782
1/
#783
10
#785
0&
#786
17
03
0;
#787
0/
#788
00
#790
1&
#791
07
13
1;
#792
1/
#793
10
#795
0&
#796
17
03
0;
#797
0/
#798
00
#800
1&
#801
07
13
1;
#802
1/
#803
10
#805
0&
#806
17
03
0;
#807
0/
#808
00
#810
1&
#811
07
13
1;
#812
1/
#813
10
#815
0&
#816
17
03
0;
#817
0/
#818
00
#820
1&
#821
07
13
1;
#822
1/
#823
10
#825
0&
#826
17
03
0;
#827
0/
#828
00
#830
1&
#831
07
13
1;
#832
1/
#833
10
#835
0&
#836
17
03
0;
#837
0/
#838
00
#840
1&
#841
07
13
1;
#842
1/
#843
10
#845
0&
#846
17
03
0;
#847
0/
#848
00
#850
1&
#851
07
13
1;
#852
1/
#853
10
#855
0&
#856
17
03
0;
#857
0/
#858
00
#860
1&
#861
07
13
1;
#862
1/
#863
10
#865
0&
#866
17
03
0;
#867
0/
#868
00
#870
1&
#871
07
13
1;
#872
1/
#873
10
#875
0&
#876
17
03
0;
#877
0/
#878
00
#880
1&
#881
07
13
1;
#882
1/
#883
10
#885
0&
#886
17
03
0;
#887
0/
#888
00
#890
1&
#891
07
13
1;
#892
1/
#893
10
#895
0&
#896
17
03
0;
#897
0/
#898
00
#900
1&
#901
07
13
1;
#902
1/
#903
10
#905
0&
#906
17
03
0;
#907
0/
#908
00
#910
1&
#911
07
13
1;
#912
1/
#913
10
#915
0&
#916
17
03
0;
#917
0/
#918
00
#920
1&
#921
07
13
1;
#922
1/
#923
10
#925
0&
#926
17
03
0;
#927
0/
#928
00
#930
1&
#931
07
13
1;
#932
1/
#933
10
#935
0&
#936
17
03
0;
#937
0/
#938
00
#940
1&
#941
07
13
1;
#942
1/
#943
10
#945
0&
#946
17
03
0;
#947
0/
#948
00
#950
1&
#951
07
13
1;
#952
1/
#953
10
#955
0&
#956
17
03
0;
#957
0/
#958
00
#960
1&
#961
07
13
1;
#962
1/
#963
10
#965
0&
#966
17
03
0;
#967
0/
#968
00
#970
1&
#971
07
13
1;
#972
1/
#973
10
#975
0&
#976
17
03
0;
#977
0/
#978
00
#980
1&
#981
07
13
1;
#982
1/
#983
10
#985
0&
#986
17
03
0;
#987
0/
#988
00
#990
1&
#991
07
13
1;
#992
1/
#993
10
#995
0&
#996
17
03
0;
#997
0/
#998
00
#1000
1&
#1001
07
13
1;
#1002
1/
#1003
10
#1005
0&
#1006
17
03
0;
#1007
0/
#1008
00
#1010
1&
#1011
07
13
1;
#1012
1/
#1013
10
#1015
0&
#1016
17
03
0;
#1017
0/
#1018
00
#1020
1&
#1021
07
13
1;
#1022
1/
#1023
10
#1025
0&
#1026
17
03
0;
#1027
0/
#1028
00
#1030
1&
#1031
07
13
1;
#1032
1/
#1033
10
#1035
0&
#1036
17
03
0;
#1037
0/
#1038
00
#1040
1&
#1041
07
13
1;
#1042
1/
#1043
10
#1045
0&
#1046
17
03
0;
#1047
0/
#1048
00
#1050
1&
#1051
07
13
1;
#1052
1/
#1053
10
#1055
0&
#1056
17
03
0;
#1057
0/
#1058
00
#1060
1&
#1061
07
13
1;
#1062
1/
#1063
10
#1065
0&
#1066
17
03
0;
#1067
0/
#1068
00
#1070
1&
#1071
07
13
1;
#1072
1/
#1073
10
#1075
0&
#1076
17
03
0;
#1077
0/
#1078
00
#1080
1&
#1081
07
13
1;
#1082
1/
#1083
10
#1085
0&
#1086
17
03
0;
#1087
0/
#1088
00
#1090
1&
#1091
07
13
1;
#1092
1/
#1093
10
#1095
0&
#1096
17
03
0;
#1097
0/
#1098
00
#1100
1&
#1101
07
13
1;
#1102
1/
#1103
10
#1105
0&
#1106
17
03
0;
#1107
0/
#1108
00
#1110
1&
#1111
07
13
1;
#1112
1/
#1113
10
#1115
0&
#1116
17
03
0;
#1117
0/
#1118
00
#1120
1&
#1121
07
13
1;
#1122
1/
#1123
10
#1125
0&
#1126
17
03
0;
#1127
0/
#1128
00
#1130
1&
#1131
07
13
1;
#1132
1/
#1133
10
#1135
0&
#1136
17
03
0;
#1137
0/
#1138
00
#1140
1&
#1141
07
13
1;
#1142
1/
#1143
10
#1145
0&
#1146
17
03
0;
#1147
0/
#1148
00
#1150
1&
#1151
07
13
1;
#1152
1/
#1153
10
#1155
0&
#1156
17
03
0;
#1157
0/
#1158
00
#1160
1&
#1161
07
13
1;
#1162
1/
#1163
10
#1165
0&
#1166
17
03
0;
#1167
0/
#1168
00
#1170
1&
#1171
07
13
1;
#1172
1/
#1173
10
#1175
0&
#1176
17
03
0;
#1177
0/
#1178
00
#1180
1&
#1181
07
13
1;
#1182
1/
#1183
10
#1185
0&
#1186
17
03
0;
#1187
0/
#1188
00
#1190
1&
#1191
07
13
1;
#1192
1/
#1193
10
#1195
0&
#1196
17
03
0;
#1197
0/
#1198
00
#1200
1&
#1201
07
13
1;
#1202
1/
#1203
10
#1205
0&
#1206
17
03
0;
#1207
0/
#1208
00
#1210
1&
#1211
07
13
1;
#1212
1/
#1213
10
#1215
0&
#1216
17
03
0;
#1217
0/
#1218
00
#1220
1&
#1221
07
13
1;
#1222
1/
#1223
10
#1225
0&
#1226
17
03
0;
#1227
0/
#1228
00
#1230
1&
#1231
07
13
1;
#1232
1/
#1233
10
#1235
0&
#1236
17
03
0;
#1237
0/
#1238
00
#1240
1&
#1241
07
13
1;
#1242
1/
#1243
10
#1245
0&
#1246
17
03
0;
#1247
0/
#1248
00
#1250
1&
#1251
07
13
1;
#1252
1/
#1253
10
#1255
0&
#1256
17
03
0;
#1257
0/
#1258
00
#1260
1&
#1261
07
13
1;
#1262
1/
#1263
10
#1265
0&
#1266
17
03
0;
#1267
0/
#1268
00
#1270
1&
#1271
07
13
1;
#1272
1/
#1273
10
#1275
0&
#1276
17
03
0;
#1277
0/
#1278
00
#1280
1&
#1281
07
13
1;
#1282
1/
#1283
10
#1285
0&
#1286
17
03
0;
#1287
0/
#1288
00
#1290
1&
#1291
07
13
1;
#1292
1/
#1293
10
#1295
0&
#1296
17
03
0;
#1297
0/
#1298
00
#1300
1&
#1301
07
13
1;
#1302
1/
#1303
10
#1305
0&
#1306
17
03
0;
#1307
0/
#1308
00
#1310
1&
#1311
07
13
1;
#1312
1/
#1313
10
#1315
0&
#1316
17
03
0;
#1317
0/
#1318
00
#1320
1&
#1321
07
13
1;
#1322
1/
#1323
10
#1325
0&
#1326
17
03
0;
#1327
0/
#1328
00
#1330
1&
#1331
07
13
1;
#1332
1/
#1333
10
#1335
0&
#1336
17
03
0;
#1337
0/
#1338
00
#1340
1&
#1341
07
13
1;
#1342
1/
#1343
10
#1345
0&
#1346
17
03
0;
#1347
0/
#1348
00
#1350
1&
#1351
07
13
1;
#1352
1/
#1353
10
#1355
0&
#1356
17
03
0;
#1357
0/
#1358
00
#1360
1&
#1361
07
13
1;
#1362
1/
#1363
10
#1365
0&
#1366
17
03
0;
#1367
0/
#1368
00
#1370
1&
#1371
07
13
1;
#1372
1/
#1373
10
#1375
0&
#1376
17
03
0;
#1377
0/
#1378
00
#1380
1&
#1381
07
13
1;
#1382
1/
#1383
10
#1385
0&
#1386
17
03
0;
#1387
0/
#1388
00
#1390
1&
#1391
07
13
1;
#1392
1/
#1393
10
#1395
0&
#1396
17
03
0;
#1397
0/
#1398
00
#1400
1&
#1401
07
13
1;
#1402
1/
#1403
10
#1405
0&
#1406
17
03
0;
#1407
0/
#1408
00
#1410
1&
#1411
07
13
1;
#1412
1/
#1413
10
#1415
0&
#1416
17
03
0;
#1417
0/
#1418
00
#1420
1&
#1421
07
13
1;
#1422
1/
#1423
10
#1425
0&
#1426
17
03
0;
#1427
0/
#1428
00
#1430
1&
#1431
07
13
1;
#1432
1/
#1433
10
#1435
0&
#1436
17
03
0;
#1437
0/
#1438
00
#1440
1&
#1441
07
13
1;
#1442
1/
#1443
10
#1445
0&
#1446
17
03
0;
#1447
0/
#1448
00
#1450
1&
#1451
07
13
1;
#1452
1/
#1453
10
#1455
0&
#1456
17
03
0;
#1457
0/
#1458
00
#1460
1&
#1461
07
13
1;
#1462
1/
#1463
10
#1465
0&
#1466
17
03
0;
#1467
0/
#1468
00
#1470
1&
#1471
07
13
1;
#1472
1/
#1473
10
#1475
0&
#1476
17
03
0;
#1477
0/
#1478
00
#1480
1&
#1481
07
13
1;
#1482
1/
#1483
10
#1485
0&
#1486
17
03
0;
#1487
0/
#1488
00
#1490
1&
#1491
07
13
1;
#1492
1/
#1493
10
#1495
0&
#1496
17
03
0;
#1497
0/
#1498
00
#1500
1&
#1501
07
13
1;
#1502
1/
#1503
10
#1505
0&
#1506
17
03
0;
#1507
0/
#1508
00
#1510
1&
#1511
07
13
1;
#1512
1/
#1513
10
#1515
0&
#1516
17
03
0;
#1517
0/
#1518
00
#1520
1&
#1521
07
13
1;
#1522
1/
#1523
10
#1525
0&
#1526
17
03
0;
#1527
0/
#1528
00
#1530
1&
#1531
07
13
1;
#1532
1/
#1533
10
#1535
0&
#1536
17
03
0;
#1537
0/
#1538
00
#1540
1&
#1541
07
13
1;
#1542
1/
#1543
10
#1545
0&
#1546
17
03
0;
#1547
0/
#1548
00
#1550
1&
#1551
07
13
1;
#1552
1/
#1553
10
#1555
0&
#1556
17
03
0;
#1557
0/
#1558
00
#1560
1&
#1561
07
13
1;
#1562
1/
#1563
10
#1565
0&
#1566
17
03
0;
#1567
0/
#1568
00
#1570
1&
#1571
07
13
1;
#1572
1/
#1573
10
#1575
0&
#1576
17
03
0;
#1577
0/
#1578
00
#1580
1&
#1581
07
13
1;
#1582
1/
#1583
10
#1585
0&
#1586
17
03
0;
#1587
0/
#1588
00
#1590
1&
#1591
07
13
1;
#1592
1/
#1593
10
#1595
0&
#1596
17
03
0;
#1597
0/
#1598
00
#1600
1&
#1601
07
13
1;
#1602
1/
#1603
10
#1605
0&
#1606
17
03
0;
#1607
0/
#1608
00
#1610
1&
#1611
07
13
1;
#1612
1/
#1613
10
#1615
0&
#1616
17
03
0;
#1617
0/
#1618
00
#1620
1&
#1621
07
13
1;
#1622
1/
#1623
10
#1625
0&
#1626
17
03
0;
#1627
0/
#1628
00
#1630
1&
#1631
07
13
1;
#1632
1/
#1633
10
#1635
0&
#1636
17
03
0;
#1637
0/
#1638
00
#1640
1&
#1641
07
13
1;
#1642
1/
#1643
10
#1645
0&
#1646
17
03
0;
#1647
0/
#1648
00
#1650
1&
#1651
07
13
1;
#1652
1/
#1653
10
#1655
0&
#1656
17
03
0;
#1657
0/
#1658
00
#1660
1&
#1661
07
13
1;
#1662
1/
#1663
10
#1665
0&
#1666
17
03
0;
#1667
0/
#1668
00
#1670
1&
#1671
07
13
1;
#1672
1/
#1673
10
#1675
0&
#1676
17
03
0;
#1677
0/
#1678
00
#1680
1&
#1681
07
13
1;
#1682
1/
#1683
10
#1685
0&
#1686
17
03
0;
#1687
0/
#1688
00
#1690
1&
#1691
07
13
1;
#1692
1/
#1693
10
#1695
0&
#1696
17
03
0;
#1697
0/
#1698
00
#1700
1&
#1701
07
13
1;
#1702
1/
#1703
10
#1705
0&
#1706
17
03
0;
#1707
0/
#1708
00
#1710
1&
#1711
07
13
1;
#1712
1/
#1713
10
#1715
0&
#1716
17
03
0;
#1717
0/
#1718
00
#1720
1&
#1721
07
13
1;
#1722
1/
#1723
10
#1725
0&
#1726
17
03
0;
#1727
0/
#1728
00
#1730
1&
#1731
07
13
1;
#1732
1/
#1733
10
#1735
0&
#1736
17
03
0;
#1737
0/
#1738
00
#1740
1&
#1741
07
13
1;
#1742
1/
#1743
10
#1745
0&
#1746
17
03
0;
#1747
0/
#1748
00
#1750
1&
#1751
07
13
1;
#1752
1/
#1753
10
#1755
0&
#1756
17
03
0;
#1757
0/
#1758
00
#1760
1&
#1761
07
13
1;
#1762
1/
#1763
10
#1765
0&
#1766
17
03
0;
#1767
0/
#1768
00
#1770
1&
#1771
07
13
1;
#1772
1/
#1773
10
#1775
0&
#1776
17
03
0;
#1777
0/
#1778
00
#1780
1&
#1781
07
13
1;
#1782
1/
#1783
10
#1785
0&
#1786
17
03
0;
#1787
0/
#1788
00
#1790
1&
#1791
07
13
1;
#1792
1/
#1793
10
#1795
0&
#1796
17
03
0;
#1797
0/
#1798
00
#1800
1&
#1801
07
13
1;
#1802
1/
#1803
10
#1805
0&
#1806
17
03
0;
#1807
0/
#1808
00
#1810
1&
#1811
07
13
1;
#1812
1/
#1813
10
#1815
0&
#1816
17
03
0;
#1817
0/
#1818
00
#1820
1&
#1821
07
13
1;
#1822
1/
#1823
10
#1825
0&
#1826
17
03
0;
#1827
0/
#1828
00
#1830
1&
#1831
07
13
1;
#1832
1/
#1833
10
#1835
0&
#1836
17
03
0;
#1837
0/
#1838
00
#1840
1&
#1841
07
13
1;
#1842
1/
#1843
10
#1845
0&
#1846
17
03
0;
#1847
0/
#1848
00
#1850
1&
#1851
07
13
1;
#1852
1/
#1853
10
#1855
0&
#1856
17
03
0;
#1857
0/
#1858
00
#1860
1&
#1861
07
13
1;
#1862
1/
#1863
10
#1865
0&
#1866
17
03
0;
#1867
0/
#1868
00
#1870
1&
#1871
07
13
1;
#1872
1/
#1873
10
#1875
0&
#1876
17
03
0;
#1877
0/
#1878
00
#1880
1&
#1881
07
13
1;
#1882
1/
#1883
10
#1885
0&
#1886
17
03
0;
#1887
0/
#1888
00
#1890
1&
#1891
07
13
1;
#1892
1/
#1893
10
#1895
0&
#1896
17
03
0;
#1897
0/
#1898
00
#1900
1&
#1901
07
13
1;
#1902
1/
#1903
10
#1905
0&
#1906
17
03
0;
#1907
0/
#1908
00
#1910
1&
#1911
07
13
1;
#1912
1/
#1913
10
#1915
0&
#1916
17
03
0;
#1917
0/
#1918
00
#1920
1&
#1921
07
13
1;
#1922
1/
#1923
10
#1925
0&
#1926
17
03
0;
#1927
0/
#1928
00
#1930
1&
#1931
07
13
1;
#1932
1/
#1933
10
#1935
0&
#1936
17
03
0;
#1937
0/
#1938
00
#1940
1&
#1941
07
13
1;
#1942
1/
#1943
10
#1945
0&
#1946
17
03
0;
#1947
0/
#1948
00
#1950
1&
#1951
07
13
1;
#1952
1/
#1953
10
#1955
0&
#1956
17
03
0;
#1957
0/
#1958
00
#1960
1&
#1961
07
13
1;
#1962
1/
#1963
10
#1965
0&
#1966
17
03
0;
#1967
0/
#1968
00
#1970
1&
#1971
07
13
1;
#1972
1/
#1973
10
#1975
0&
#1976
17
03
0;
#1977
0/
#1978
00
#1980
1&
#1981
07
13
1;
#1982
1/
#1983
10
#1985
0&
#1986
17
03
0;
#1987
0/
#1988
00
#1990
1&
#1991
07
13
1;
#1992
1/
#1993
10
#1995
0&
#1996
17
03
0;
#1997
0/
#1998
00
#2000
1&
#2001
07
13
1;
#2002
1/
#2003
10
#2005
0&
#2006
17
03
0;
#2007
0/
#2008
00
#2010
1&
#2011
07
13
1;
#2012
1/
#2013
10
#2015
0&
#2016
17
03
0;
#2017
0/
#2018
00
#2020
1&
#2021
07
13
1;
#2022
1/
#2023
10
#2025
0&
#2026
17
03
0;
#2027
0/
#2028
00
#2030
1&
#2031
07
13
1;
#2032
1/
#2033
10
#2035
0&
#2036
17
03
0;
#2037
0/
#2038
00
#2040
1&
#2041
07
13
1;
#2042
1/
#2043
10
#2045
0&
#2046
17
03
0;
#2047
0/
#2048
00
#2050
1&
#2051
07
13
1;
#2052
1/
#2053
10
#2055
0&
#2056
17
03
0;
#2057
0/
#2058
00
#2060
1&
#2061
07
13
1;
#2062
1/
#2063
10
#2065
0&
#2066
17
03
0;
#2067
0/
#2068
00
#2070
1&
#2071
07
13
1;
#2072
1/
#2073
10
#2075
0&
#2076
17
03
0;
#2077
0/
#2078
00
#2080
1&
#2081
07
13
1;
#2082
1/
#2083
10
#2085
0&
#2086
17
03
0;
#2087
0/
#2088
00
#2090
1&
#2091
07
13
1;
#2092
1/
#2093
10
#2095
0&
#2096
17
03
0;
#2097
0/
#2098
00
#2100
1&
#2101
07
13
1;
#2102
1/
#2103
10
#2105
0&
#2106
17
03
0;
#2107
0/
#2108
00
#2110
1&
#2111
07
13
1;
#2112
1/
#2113
10
#2115
0&
#2116
17
03
0;
#2117
0/
#2118
00
#2120
1&
#2121
07
13
1;
#2122
1/
#2123
10
#2125
0&
#2126
17
03
0;
#2127
0/
#2128
00
#2130
1&
#2131
07
13
1;
#2132
1/
#2133
10
#2135
0&
#2136
17
03
0;
#2137
0/
#2138
00
#2140
1&
#2141
07
13
1;
#2142
1/
#2143
10
#2145
0&
#2146
17
03
0;
#2147
0/
#2148
00
#2150
1&
#2151
07
13
1;
#2152
1/
#2153
10
#2155
0&
#2156
17
03
0;
#2157
0/
#2158
00
#2160
1&
#2161
07
13
1;
#2162
1/
#2163
10
#2165
0&
#2166
17
03
0;
#2167
0/
#2168
00
#2170
1&
#2171
07
13
1;
#2172
1/
#2173
10
#2175
0&
#2176
17
03
0;
#2177
0/
#2178
00
#2180
1&
#2181
07
13
1;
#2182
1/
#2183
10
#2185
0&
#2186
17
03
0;
#2187
0/
#2188
00
#2190
1&
#2191
07
13
1;
#2192
1/
#2193
10
#2195
0&
#2196
17
03
0;
#2197
0/
#2198
00
#2200
1&
#2201
07
13
1;
#2202
1/
#2203
10
#2205
0&
